fakeproj/__init__.py
fakeproj/fakedir/__init__.py
fakeproj/fakedir/fakemodule.py
fakeproj/gooddir/__init__.py
fakeproj/gooddir/goodmodule.py
fakeproj/gooddir/sysmodule.py
fakeproj/slowdir/__init__.py
fakeproj/slowdir/slowmodule.py
fakeproj-1.0.dist-info/METADATA
fakeproj-1.0.dist-info/WHEEL
fakeproj-1.0.dist-info/top_level.txt
fakeproj-1.0.dist-info/RECORD
