Metadata-Version: 2.1
Name: fakeproj
Version: 1.0
Summary: Mostly useless code to demonstrate Python DevOps tools
Home-page: https://github.com/lazyoracle/fakeproj
Author: Anurag Saha Roy
Author-email: anurag.roni@gmail.com
License: UNKNOWN
Platform: UNKNOWN
Classifier: Programming Language :: Python :: 3
Classifier: License :: OSI Approved :: MIT License
Classifier: Operating System :: OS Independent
Classifier: Development Status :: 4 - Beta
Classifier: Intended Audience :: Developers
Classifier: Topic :: Software Development :: Build Tools
Requires-Python: >=3.6
Requires-Dist: numpy (==1.19.0)
